monopylib/__init__.py
monopylib/common/__init__.py
monopylib/common/config_manager.py
monopylib/common/dependency_manager.py
monopylib/common/file_manager.py
monopylib/common/logging_config.py
monopylib/init/__init__.py
monopylib/init/case_manager.py
monopylib/init/cli.py
monopylib/init/installation.py
monopylib/init/service_runner.py
monopylib-0.1.0.dist-info/METADATA
monopylib-0.1.0.dist-info/WHEEL
monopylib-0.1.0.dist-info/entry_points.txt
monopylib-0.1.0.dist-info/top_level.txt
monopylib-0.1.0.dist-info/RECORD
