Metadata-Version: 2.1
Name: monopylib
Version: 0.1.0
Summary: Tool for managing Python monorepos
Home-page: https://gitlab.com/yakov.perets/python-monorepo-simulation
Author: Yakov Perets
Author-email: yakov.perets@gmail.com
Classifier: Programming Language :: Python :: 3
Classifier: License :: OSI Approved :: MIT License
Classifier: Operating System :: OS Independent
Requires-Python: >=3.6
Requires-Dist: click
